{
  "family": "webapp-devops-workshop",
  "taskRoleArn": "arn:aws:iam::536910021553:role/devops-cluster-TaskRole-5t89EHbP71DA",
  "executionRoleArn": "arn:aws:iam::536910021553:role/ECSTaskExecutionRole",
  "networkMode": "awsvpc",
  "containerDefinitions": [
    {
      "name": "webapp",
      "cpu": 0,
      "image": "<IMAGE1_NAME>",
      "links": [],
      "portMappings": [
        {
          "containerPort": 80,
          "hostPort": 80,
          "protocol": "tcp"
        }
      ],
      "essential": true,
      "entryPoint": [],
      "command": [],
      "environment": [],
      "environmentFiles": [],
      "mountPoints": [],
      "volumesFrom": [],
      "secrets": [],
      "dnsServers": [],
      "dnsSearchDomains": [],
      "extraHosts": [],
      "dockerSecurityOptions": [],
      "dockerLabels": {},
      "ulimits": [],
      "systemControls": [],
      "credentialSpecs": []
    }
  ],
  "volumes": [],
  "placementConstraints": [],
  "requiresCompatibilities": [
    "FARGATE"
  ],
  "cpu": "256",
  "memory": "512"
}
